{
  "_format": "hh-sol-cache-2",
  "files": {
    "D:\\Trading Contracts\\TradingWithCrypto Hardhat Test\\contracts\\allowances.sol": {
      "lastModificationDate": 1672905985785,
      "contentHash": "4a22251deb33eb8976a3f84b7dd1ca63",
      "sourceName": "contracts/allowances.sol",
      "solcConfig": {
        "version": "0.8.9",
        "settings": {
          "optimizer": {
            "enabled": false,
            "runs": 200
          },
          "outputSelection": {
            "*": {
              "*": [
                "abi",
                "evm.bytecode",
                "evm.deployedBytecode",
                "evm.methodIdentifiers",
                "metadata"
              ],
              "": [
                "ast"
              ]
            }
          }
        }
      },
      "imports": [
        "@openzeppelin/contracts/access/Ownable.sol",
        "@openzeppelin/contracts/utils/structs/EnumerableSet.sol"
      ],
      "versionPragmas": [
        "^0.8.4"
      ],
      "artifacts": [
        "Allowances"
      ]
    },
    "D:\\Trading Contracts\\TradingWithCrypto Hardhat Test\\node_modules\\@openzeppelin\\contracts\\access\\Ownable.sol": {
      "lastModificationDate": 1672912027015,
      "contentHash": "e436cea06129be2c73cda4b1acc848b5",
      "sourceName": "@openzeppelin/contracts/access/Ownable.sol",
      "solcConfig": {
        "version": "0.8.9",
        "settings": {
          "optimizer": {
            "enabled": false,
            "runs": 200
          },
          "outputSelection": {
            "*": {
              "*": [
                "abi",
                "evm.bytecode",
                "evm.deployedBytecode",
                "evm.methodIdentifiers",
                "metadata"
              ],
              "": [
                "ast"
              ]
            }
          }
        }
      },
      "imports": [
        "../utils/Context.sol"
      ],
      "versionPragmas": [
        "^0.8.0"
      ],
      "artifacts": [
        "Ownable"
      ]
    },
    "D:\\Trading Contracts\\TradingWithCrypto Hardhat Test\\node_modules\\@openzeppelin\\contracts\\utils\\structs\\EnumerableSet.sol": {
      "lastModificationDate": 1672912026728,
      "contentHash": "6116ca703456923afc88ce24b466ac80",
      "sourceName": "@openzeppelin/contracts/utils/structs/EnumerableSet.sol",
      "solcConfig": {
        "version": "0.8.9",
        "settings": {
          "optimizer": {
            "enabled": false,
            "runs": 200
          },
          "outputSelection": {
            "*": {
              "*": [
                "abi",
                "evm.bytecode",
                "evm.deployedBytecode",
                "evm.methodIdentifiers",
                "metadata"
              ],
              "": [
                "ast"
              ]
            }
          }
        }
      },
      "imports": [],
      "versionPragmas": [
        "^0.8.0"
      ],
      "artifacts": [
        "EnumerableSet"
      ]
    },
    "D:\\Trading Contracts\\TradingWithCrypto Hardhat Test\\node_modules\\@openzeppelin\\contracts\\utils\\Context.sol": {
      "lastModificationDate": 1672912026696,
      "contentHash": "5f2c5c4b6af2dd4551027144797bc8be",
      "sourceName": "@openzeppelin/contracts/utils/Context.sol",
      "solcConfig": {
        "version": "0.8.9",
        "settings": {
          "optimizer": {
            "enabled": false,
            "runs": 200
          },
          "outputSelection": {
            "*": {
              "*": [
                "abi",
                "evm.bytecode",
                "evm.deployedBytecode",
                "evm.methodIdentifiers",
                "metadata"
              ],
              "": [
                "ast"
              ]
            }
          }
        }
      },
      "imports": [],
      "versionPragmas": [
        "^0.8.0"
      ],
      "artifacts": [
        "Context"
      ]
    },
    "D:\\Trading Contracts\\TradingWithCrypto Hardhat Test\\contracts\\tradingInCrypto.sol": {
      "lastModificationDate": 1673267803321,
      "contentHash": "429ccc56e5d5c73c49c3bc374bb7e267",
      "sourceName": "contracts/tradingInCrypto.sol",
      "solcConfig": {
        "version": "0.8.9",
        "settings": {
          "optimizer": {
            "enabled": false,
            "runs": 200
          },
          "outputSelection": {
            "*": {
              "*": [
                "abi",
                "evm.bytecode",
                "evm.deployedBytecode",
                "evm.methodIdentifiers",
                "metadata"
              ],
              "": [
                "ast"
              ]
            }
          }
        }
      },
      "imports": [
        "./tradingInCryptoStorage.sol",
        "./allowances.sol",
        "@openzeppelin/contracts/token/ERC20/IERC20.sol",
        "@openzeppelin/contracts/access/AccessControl.sol",
        "@openzeppelin/contracts/utils/structs/EnumerableSet.sol"
      ],
      "versionPragmas": [
        "^0.8.4"
      ],
      "artifacts": [
        "tradingInCrypto"
      ]
    },
    "D:\\Trading Contracts\\TradingWithCrypto Hardhat Test\\contracts\\tradingInCryptoStorage.sol": {
      "lastModificationDate": 1673078621742,
      "contentHash": "cff67006949dc7792196da7f2e4971db",
      "sourceName": "contracts/tradingInCryptoStorage.sol",
      "solcConfig": {
        "version": "0.8.9",
        "settings": {
          "optimizer": {
            "enabled": false,
            "runs": 200
          },
          "outputSelection": {
            "*": {
              "*": [
                "abi",
                "evm.bytecode",
                "evm.deployedBytecode",
                "evm.methodIdentifiers",
                "metadata"
              ],
              "": [
                "ast"
              ]
            }
          }
        }
      },
      "imports": [],
      "versionPragmas": [
        "^0.8.4"
      ],
      "artifacts": [
        "tradingInCryptoStorage"
      ]
    },
    "D:\\Trading Contracts\\TradingWithCrypto Hardhat Test\\node_modules\\@openzeppelin\\contracts\\access\\AccessControl.sol": {
      "lastModificationDate": 1672912026672,
      "contentHash": "95a6c227d1b8843e9385518a5bce4853",
      "sourceName": "@openzeppelin/contracts/access/AccessControl.sol",
      "solcConfig": {
        "version": "0.8.9",
        "settings": {
          "optimizer": {
            "enabled": false,
            "runs": 200
          },
          "outputSelection": {
            "*": {
              "*": [
                "abi",
                "evm.bytecode",
                "evm.deployedBytecode",
                "evm.methodIdentifiers",
                "metadata"
              ],
              "": [
                "ast"
              ]
            }
          }
        }
      },
      "imports": [
        "./IAccessControl.sol",
        "../utils/Context.sol",
        "../utils/Strings.sol",
        "../utils/introspection/ERC165.sol"
      ],
      "versionPragmas": [
        "^0.8.0"
      ],
      "artifacts": [
        "AccessControl"
      ]
    },
    "D:\\Trading Contracts\\TradingWithCrypto Hardhat Test\\node_modules\\@openzeppelin\\contracts\\token\\ERC20\\IERC20.sol": {
      "lastModificationDate": 1672912026864,
      "contentHash": "ad7c2d0af148c8f9f097d65deeb4da6b",
      "sourceName": "@openzeppelin/contracts/token/ERC20/IERC20.sol",
      "solcConfig": {
        "version": "0.8.9",
        "settings": {
          "optimizer": {
            "enabled": false,
            "runs": 200
          },
          "outputSelection": {
            "*": {
              "*": [
                "abi",
                "evm.bytecode",
                "evm.deployedBytecode",
                "evm.methodIdentifiers",
                "metadata"
              ],
              "": [
                "ast"
              ]
            }
          }
        }
      },
      "imports": [],
      "versionPragmas": [
        "^0.8.0"
      ],
      "artifacts": [
        "IERC20"
      ]
    },
    "D:\\Trading Contracts\\TradingWithCrypto Hardhat Test\\node_modules\\@openzeppelin\\contracts\\utils\\Strings.sol": {
      "lastModificationDate": 1672912027047,
      "contentHash": "396031251978f8febfd90cb62cb240ec",
      "sourceName": "@openzeppelin/contracts/utils/Strings.sol",
      "solcConfig": {
        "version": "0.8.9",
        "settings": {
          "optimizer": {
            "enabled": false,
            "runs": 200
          },
          "outputSelection": {
            "*": {
              "*": [
                "abi",
                "evm.bytecode",
                "evm.deployedBytecode",
                "evm.methodIdentifiers",
                "metadata"
              ],
              "": [
                "ast"
              ]
            }
          }
        }
      },
      "imports": [
        "./math/Math.sol"
      ],
      "versionPragmas": [
        "^0.8.0"
      ],
      "artifacts": [
        "Strings"
      ]
    },
    "D:\\Trading Contracts\\TradingWithCrypto Hardhat Test\\node_modules\\@openzeppelin\\contracts\\utils\\introspection\\ERC165.sol": {
      "lastModificationDate": 1672912026745,
      "contentHash": "0e7db055ce108f9da7bb6686a00287c0",
      "sourceName": "@openzeppelin/contracts/utils/introspection/ERC165.sol",
      "solcConfig": {
        "version": "0.8.9",
        "settings": {
          "optimizer": {
            "enabled": false,
            "runs": 200
          },
          "outputSelection": {
            "*": {
              "*": [
                "abi",
                "evm.bytecode",
                "evm.deployedBytecode",
                "evm.methodIdentifiers",
                "metadata"
              ],
              "": [
                "ast"
              ]
            }
          }
        }
      },
      "imports": [
        "./IERC165.sol"
      ],
      "versionPragmas": [
        "^0.8.0"
      ],
      "artifacts": [
        "ERC165"
      ]
    },
    "D:\\Trading Contracts\\TradingWithCrypto Hardhat Test\\node_modules\\@openzeppelin\\contracts\\access\\IAccessControl.sol": {
      "lastModificationDate": 1672912026824,
      "contentHash": "57c84298234411cea19c7c284d86be8b",
      "sourceName": "@openzeppelin/contracts/access/IAccessControl.sol",
      "solcConfig": {
        "version": "0.8.9",
        "settings": {
          "optimizer": {
            "enabled": false,
            "runs": 200
          },
          "outputSelection": {
            "*": {
              "*": [
                "abi",
                "evm.bytecode",
                "evm.deployedBytecode",
                "evm.methodIdentifiers",
                "metadata"
              ],
              "": [
                "ast"
              ]
            }
          }
        }
      },
      "imports": [],
      "versionPragmas": [
        "^0.8.0"
      ],
      "artifacts": [
        "IAccessControl"
      ]
    },
    "D:\\Trading Contracts\\TradingWithCrypto Hardhat Test\\node_modules\\@openzeppelin\\contracts\\utils\\math\\Math.sol": {
      "lastModificationDate": 1672912027007,
      "contentHash": "b9c58920ce74d6dc819161786112e7ee",
      "sourceName": "@openzeppelin/contracts/utils/math/Math.sol",
      "solcConfig": {
        "version": "0.8.9",
        "settings": {
          "optimizer": {
            "enabled": false,
            "runs": 200
          },
          "outputSelection": {
            "*": {
              "*": [
                "abi",
                "evm.bytecode",
                "evm.deployedBytecode",
                "evm.methodIdentifiers",
                "metadata"
              ],
              "": [
                "ast"
              ]
            }
          }
        }
      },
      "imports": [],
      "versionPragmas": [
        "^0.8.0"
      ],
      "artifacts": [
        "Math"
      ]
    },
    "D:\\Trading Contracts\\TradingWithCrypto Hardhat Test\\node_modules\\@openzeppelin\\contracts\\utils\\introspection\\IERC165.sol": {
      "lastModificationDate": 1672912026856,
      "contentHash": "03e6768535ac4da0e9756f1d8a4a018a",
      "sourceName": "@openzeppelin/contracts/utils/introspection/IERC165.sol",
      "solcConfig": {
        "version": "0.8.9",
        "settings": {
          "optimizer": {
            "enabled": false,
            "runs": 200
          },
          "outputSelection": {
            "*": {
              "*": [
                "abi",
                "evm.bytecode",
                "evm.deployedBytecode",
                "evm.methodIdentifiers",
                "metadata"
              ],
              "": [
                "ast"
              ]
            }
          }
        }
      },
      "imports": [],
      "versionPragmas": [
        "^0.8.0"
      ],
      "artifacts": [
        "IERC165"
      ]
    },
    "D:\\Trading Contracts\\TradingWithCrypto Hardhat Test\\node_modules\\@openzeppelin\\contracts\\token\\ERC20\\extensions\\IERC20Metadata.sol": {
      "lastModificationDate": 1672912026864,
      "contentHash": "909ab67fc5c25033fe6cd364f8c056f9",
      "sourceName": "@openzeppelin/contracts/token/ERC20/extensions/IERC20Metadata.sol",
      "solcConfig": {
        "version": "0.8.9",
        "settings": {
          "optimizer": {
            "enabled": false,
            "runs": 200
          },
          "outputSelection": {
            "*": {
              "*": [
                "abi",
                "evm.bytecode",
                "evm.deployedBytecode",
                "evm.methodIdentifiers",
                "metadata"
              ],
              "": [
                "ast"
              ]
            }
          }
        }
      },
      "imports": [
        "../IERC20.sol"
      ],
      "versionPragmas": [
        "^0.8.0"
      ],
      "artifacts": [
        "IERC20Metadata"
      ]
    },
    "D:\\Trading Contracts\\TradingWithCrypto Hardhat Test\\node_modules\\@openzeppelin\\contracts\\token\\ERC20\\ERC20.sol": {
      "lastModificationDate": 1672912026753,
      "contentHash": "834a0dde221759af42b030253315b086",
      "sourceName": "@openzeppelin/contracts/token/ERC20/ERC20.sol",
      "solcConfig": {
        "version": "0.8.9",
        "settings": {
          "optimizer": {
            "enabled": false,
            "runs": 200
          },
          "outputSelection": {
            "*": {
              "*": [
                "abi",
                "evm.bytecode",
                "evm.deployedBytecode",
                "evm.methodIdentifiers",
                "metadata"
              ],
              "": [
                "ast"
              ]
            }
          }
        }
      },
      "imports": [
        "./IERC20.sol",
        "./extensions/IERC20Metadata.sol",
        "../../utils/Context.sol"
      ],
      "versionPragmas": [
        "^0.8.0"
      ],
      "artifacts": [
        "ERC20"
      ]
    },
    "D:\\Trading Contracts\\TradingWithCrypto Hardhat Test\\contracts\\ERC20.sol": {
      "lastModificationDate": 1672905943449,
      "contentHash": "d8e0aab02218f77384d0406b04c63388",
      "sourceName": "contracts/ERC20.sol",
      "solcConfig": {
        "version": "0.8.9",
        "settings": {
          "optimizer": {
            "enabled": false,
            "runs": 200
          },
          "outputSelection": {
            "*": {
              "*": [
                "abi",
                "evm.bytecode",
                "evm.deployedBytecode",
                "evm.methodIdentifiers",
                "metadata"
              ],
              "": [
                "ast"
              ]
            }
          }
        }
      },
      "imports": [
        "@openzeppelin/contracts/token/ERC20/ERC20.sol",
        "@openzeppelin/contracts/access/Ownable.sol"
      ],
      "versionPragmas": [
        "^0.8.4"
      ],
      "artifacts": [
        "tradeToken"
      ]
    },
    "D:\\Trading Contracts\\TradingWithCrypto Hardhat Test\\contracts\\Lock.sol": {
      "lastModificationDate": 1672905592062,
      "contentHash": "ae66265769cc28ebdaa34881df95bc5e",
      "sourceName": "contracts/Lock.sol",
      "solcConfig": {
        "version": "0.8.9",
        "settings": {
          "optimizer": {
            "enabled": false,
            "runs": 200
          },
          "outputSelection": {
            "*": {
              "*": [
                "abi",
                "evm.bytecode",
                "evm.deployedBytecode",
                "evm.methodIdentifiers",
                "metadata"
              ],
              "": [
                "ast"
              ]
            }
          }
        }
      },
      "imports": [],
      "versionPragmas": [
        "^0.8.9"
      ],
      "artifacts": [
        "Lock"
      ]
    },
    "D:\\GITHUB REPOS\\TradeContract-Hardhat\\contracts\\allowances.sol": {
      "lastModificationDate": 1672905985785,
      "contentHash": "4a22251deb33eb8976a3f84b7dd1ca63",
      "sourceName": "contracts/allowances.sol",
      "solcConfig": {
        "version": "0.8.9",
        "settings": {
          "optimizer": {
            "enabled": false,
            "runs": 200
          },
          "outputSelection": {
            "*": {
              "*": [
                "abi",
                "evm.bytecode",
                "evm.deployedBytecode",
                "evm.methodIdentifiers",
                "metadata"
              ],
              "": [
                "ast"
              ]
            }
          }
        }
      },
      "imports": [
        "@openzeppelin/contracts/access/Ownable.sol",
        "@openzeppelin/contracts/utils/structs/EnumerableSet.sol"
      ],
      "versionPragmas": [
        "^0.8.4"
      ],
      "artifacts": [
        "Allowances"
      ]
    },
    "D:\\GITHUB REPOS\\TradeContract-Hardhat\\node_modules\\@openzeppelin\\contracts\\access\\Ownable.sol": {
      "lastModificationDate": 1672912027015,
      "contentHash": "e436cea06129be2c73cda4b1acc848b5",
      "sourceName": "@openzeppelin/contracts/access/Ownable.sol",
      "solcConfig": {
        "version": "0.8.9",
        "settings": {
          "optimizer": {
            "enabled": false,
            "runs": 200
          },
          "outputSelection": {
            "*": {
              "*": [
                "abi",
                "evm.bytecode",
                "evm.deployedBytecode",
                "evm.methodIdentifiers",
                "metadata"
              ],
              "": [
                "ast"
              ]
            }
          }
        }
      },
      "imports": [
        "../utils/Context.sol"
      ],
      "versionPragmas": [
        "^0.8.0"
      ],
      "artifacts": [
        "Ownable"
      ]
    },
    "D:\\GITHUB REPOS\\TradeContract-Hardhat\\node_modules\\@openzeppelin\\contracts\\utils\\structs\\EnumerableSet.sol": {
      "lastModificationDate": 1672912026728,
      "contentHash": "6116ca703456923afc88ce24b466ac80",
      "sourceName": "@openzeppelin/contracts/utils/structs/EnumerableSet.sol",
      "solcConfig": {
        "version": "0.8.9",
        "settings": {
          "optimizer": {
            "enabled": false,
            "runs": 200
          },
          "outputSelection": {
            "*": {
              "*": [
                "abi",
                "evm.bytecode",
                "evm.deployedBytecode",
                "evm.methodIdentifiers",
                "metadata"
              ],
              "": [
                "ast"
              ]
            }
          }
        }
      },
      "imports": [],
      "versionPragmas": [
        "^0.8.0"
      ],
      "artifacts": [
        "EnumerableSet"
      ]
    },
    "D:\\GITHUB REPOS\\TradeContract-Hardhat\\node_modules\\@openzeppelin\\contracts\\utils\\Context.sol": {
      "lastModificationDate": 1672912026696,
      "contentHash": "5f2c5c4b6af2dd4551027144797bc8be",
      "sourceName": "@openzeppelin/contracts/utils/Context.sol",
      "solcConfig": {
        "version": "0.8.9",
        "settings": {
          "optimizer": {
            "enabled": false,
            "runs": 200
          },
          "outputSelection": {
            "*": {
              "*": [
                "abi",
                "evm.bytecode",
                "evm.deployedBytecode",
                "evm.methodIdentifiers",
                "metadata"
              ],
              "": [
                "ast"
              ]
            }
          }
        }
      },
      "imports": [],
      "versionPragmas": [
        "^0.8.0"
      ],
      "artifacts": [
        "Context"
      ]
    },
    "D:\\GITHUB REPOS\\TradeContract-Hardhat\\contracts\\tradingInCrypto.sol": {
      "lastModificationDate": 1673267803321,
      "contentHash": "429ccc56e5d5c73c49c3bc374bb7e267",
      "sourceName": "contracts/tradingInCrypto.sol",
      "solcConfig": {
        "version": "0.8.9",
        "settings": {
          "optimizer": {
            "enabled": false,
            "runs": 200
          },
          "outputSelection": {
            "*": {
              "*": [
                "abi",
                "evm.bytecode",
                "evm.deployedBytecode",
                "evm.methodIdentifiers",
                "metadata"
              ],
              "": [
                "ast"
              ]
            }
          }
        }
      },
      "imports": [
        "./tradingInCryptoStorage.sol",
        "./allowances.sol",
        "@openzeppelin/contracts/token/ERC20/IERC20.sol",
        "@openzeppelin/contracts/access/AccessControl.sol",
        "@openzeppelin/contracts/utils/structs/EnumerableSet.sol"
      ],
      "versionPragmas": [
        "^0.8.4"
      ],
      "artifacts": [
        "tradingInCrypto"
      ]
    },
    "D:\\GITHUB REPOS\\TradeContract-Hardhat\\contracts\\tradingInCryptoStorage.sol": {
      "lastModificationDate": 1673078621742,
      "contentHash": "cff67006949dc7792196da7f2e4971db",
      "sourceName": "contracts/tradingInCryptoStorage.sol",
      "solcConfig": {
        "version": "0.8.9",
        "settings": {
          "optimizer": {
            "enabled": false,
            "runs": 200
          },
          "outputSelection": {
            "*": {
              "*": [
                "abi",
                "evm.bytecode",
                "evm.deployedBytecode",
                "evm.methodIdentifiers",
                "metadata"
              ],
              "": [
                "ast"
              ]
            }
          }
        }
      },
      "imports": [],
      "versionPragmas": [
        "^0.8.4"
      ],
      "artifacts": [
        "tradingInCryptoStorage"
      ]
    },
    "D:\\GITHUB REPOS\\TradeContract-Hardhat\\node_modules\\@openzeppelin\\contracts\\access\\AccessControl.sol": {
      "lastModificationDate": 1672912026672,
      "contentHash": "95a6c227d1b8843e9385518a5bce4853",
      "sourceName": "@openzeppelin/contracts/access/AccessControl.sol",
      "solcConfig": {
        "version": "0.8.9",
        "settings": {
          "optimizer": {
            "enabled": false,
            "runs": 200
          },
          "outputSelection": {
            "*": {
              "*": [
                "abi",
                "evm.bytecode",
                "evm.deployedBytecode",
                "evm.methodIdentifiers",
                "metadata"
              ],
              "": [
                "ast"
              ]
            }
          }
        }
      },
      "imports": [
        "./IAccessControl.sol",
        "../utils/Context.sol",
        "../utils/Strings.sol",
        "../utils/introspection/ERC165.sol"
      ],
      "versionPragmas": [
        "^0.8.0"
      ],
      "artifacts": [
        "AccessControl"
      ]
    },
    "D:\\GITHUB REPOS\\TradeContract-Hardhat\\node_modules\\@openzeppelin\\contracts\\token\\ERC20\\IERC20.sol": {
      "lastModificationDate": 1672912026864,
      "contentHash": "ad7c2d0af148c8f9f097d65deeb4da6b",
      "sourceName": "@openzeppelin/contracts/token/ERC20/IERC20.sol",
      "solcConfig": {
        "version": "0.8.9",
        "settings": {
          "optimizer": {
            "enabled": false,
            "runs": 200
          },
          "outputSelection": {
            "*": {
              "*": [
                "abi",
                "evm.bytecode",
                "evm.deployedBytecode",
                "evm.methodIdentifiers",
                "metadata"
              ],
              "": [
                "ast"
              ]
            }
          }
        }
      },
      "imports": [],
      "versionPragmas": [
        "^0.8.0"
      ],
      "artifacts": [
        "IERC20"
      ]
    },
    "D:\\GITHUB REPOS\\TradeContract-Hardhat\\node_modules\\@openzeppelin\\contracts\\utils\\Strings.sol": {
      "lastModificationDate": 1672912027047,
      "contentHash": "396031251978f8febfd90cb62cb240ec",
      "sourceName": "@openzeppelin/contracts/utils/Strings.sol",
      "solcConfig": {
        "version": "0.8.9",
        "settings": {
          "optimizer": {
            "enabled": false,
            "runs": 200
          },
          "outputSelection": {
            "*": {
              "*": [
                "abi",
                "evm.bytecode",
                "evm.deployedBytecode",
                "evm.methodIdentifiers",
                "metadata"
              ],
              "": [
                "ast"
              ]
            }
          }
        }
      },
      "imports": [
        "./math/Math.sol"
      ],
      "versionPragmas": [
        "^0.8.0"
      ],
      "artifacts": [
        "Strings"
      ]
    },
    "D:\\GITHUB REPOS\\TradeContract-Hardhat\\node_modules\\@openzeppelin\\contracts\\utils\\introspection\\ERC165.sol": {
      "lastModificationDate": 1672912026745,
      "contentHash": "0e7db055ce108f9da7bb6686a00287c0",
      "sourceName": "@openzeppelin/contracts/utils/introspection/ERC165.sol",
      "solcConfig": {
        "version": "0.8.9",
        "settings": {
          "optimizer": {
            "enabled": false,
            "runs": 200
          },
          "outputSelection": {
            "*": {
              "*": [
                "abi",
                "evm.bytecode",
                "evm.deployedBytecode",
                "evm.methodIdentifiers",
                "metadata"
              ],
              "": [
                "ast"
              ]
            }
          }
        }
      },
      "imports": [
        "./IERC165.sol"
      ],
      "versionPragmas": [
        "^0.8.0"
      ],
      "artifacts": [
        "ERC165"
      ]
    },
    "D:\\GITHUB REPOS\\TradeContract-Hardhat\\node_modules\\@openzeppelin\\contracts\\access\\IAccessControl.sol": {
      "lastModificationDate": 1672912026824,
      "contentHash": "57c84298234411cea19c7c284d86be8b",
      "sourceName": "@openzeppelin/contracts/access/IAccessControl.sol",
      "solcConfig": {
        "version": "0.8.9",
        "settings": {
          "optimizer": {
            "enabled": false,
            "runs": 200
          },
          "outputSelection": {
            "*": {
              "*": [
                "abi",
                "evm.bytecode",
                "evm.deployedBytecode",
                "evm.methodIdentifiers",
                "metadata"
              ],
              "": [
                "ast"
              ]
            }
          }
        }
      },
      "imports": [],
      "versionPragmas": [
        "^0.8.0"
      ],
      "artifacts": [
        "IAccessControl"
      ]
    },
    "D:\\GITHUB REPOS\\TradeContract-Hardhat\\node_modules\\@openzeppelin\\contracts\\utils\\math\\Math.sol": {
      "lastModificationDate": 1672912027007,
      "contentHash": "b9c58920ce74d6dc819161786112e7ee",
      "sourceName": "@openzeppelin/contracts/utils/math/Math.sol",
      "solcConfig": {
        "version": "0.8.9",
        "settings": {
          "optimizer": {
            "enabled": false,
            "runs": 200
          },
          "outputSelection": {
            "*": {
              "*": [
                "abi",
                "evm.bytecode",
                "evm.deployedBytecode",
                "evm.methodIdentifiers",
                "metadata"
              ],
              "": [
                "ast"
              ]
            }
          }
        }
      },
      "imports": [],
      "versionPragmas": [
        "^0.8.0"
      ],
      "artifacts": [
        "Math"
      ]
    },
    "D:\\GITHUB REPOS\\TradeContract-Hardhat\\node_modules\\@openzeppelin\\contracts\\utils\\introspection\\IERC165.sol": {
      "lastModificationDate": 1672912026856,
      "contentHash": "03e6768535ac4da0e9756f1d8a4a018a",
      "sourceName": "@openzeppelin/contracts/utils/introspection/IERC165.sol",
      "solcConfig": {
        "version": "0.8.9",
        "settings": {
          "optimizer": {
            "enabled": false,
            "runs": 200
          },
          "outputSelection": {
            "*": {
              "*": [
                "abi",
                "evm.bytecode",
                "evm.deployedBytecode",
                "evm.methodIdentifiers",
                "metadata"
              ],
              "": [
                "ast"
              ]
            }
          }
        }
      },
      "imports": [],
      "versionPragmas": [
        "^0.8.0"
      ],
      "artifacts": [
        "IERC165"
      ]
    },
    "D:\\GITHUB REPOS\\TradeContract-Hardhat\\node_modules\\@openzeppelin\\contracts\\token\\ERC20\\extensions\\IERC20Metadata.sol": {
      "lastModificationDate": 1672912026864,
      "contentHash": "909ab67fc5c25033fe6cd364f8c056f9",
      "sourceName": "@openzeppelin/contracts/token/ERC20/extensions/IERC20Metadata.sol",
      "solcConfig": {
        "version": "0.8.9",
        "settings": {
          "optimizer": {
            "enabled": false,
            "runs": 200
          },
          "outputSelection": {
            "*": {
              "*": [
                "abi",
                "evm.bytecode",
                "evm.deployedBytecode",
                "evm.methodIdentifiers",
                "metadata"
              ],
              "": [
                "ast"
              ]
            }
          }
        }
      },
      "imports": [
        "../IERC20.sol"
      ],
      "versionPragmas": [
        "^0.8.0"
      ],
      "artifacts": [
        "IERC20Metadata"
      ]
    },
    "D:\\GITHUB REPOS\\TradeContract-Hardhat\\node_modules\\@openzeppelin\\contracts\\token\\ERC20\\ERC20.sol": {
      "lastModificationDate": 1672912026753,
      "contentHash": "834a0dde221759af42b030253315b086",
      "sourceName": "@openzeppelin/contracts/token/ERC20/ERC20.sol",
      "solcConfig": {
        "version": "0.8.9",
        "settings": {
          "optimizer": {
            "enabled": false,
            "runs": 200
          },
          "outputSelection": {
            "*": {
              "*": [
                "abi",
                "evm.bytecode",
                "evm.deployedBytecode",
                "evm.methodIdentifiers",
                "metadata"
              ],
              "": [
                "ast"
              ]
            }
          }
        }
      },
      "imports": [
        "./IERC20.sol",
        "./extensions/IERC20Metadata.sol",
        "../../utils/Context.sol"
      ],
      "versionPragmas": [
        "^0.8.0"
      ],
      "artifacts": [
        "ERC20"
      ]
    },
    "D:\\GITHUB REPOS\\TradeContract-Hardhat\\contracts\\ERC20.sol": {
      "lastModificationDate": 1672905943449,
      "contentHash": "d8e0aab02218f77384d0406b04c63388",
      "sourceName": "contracts/ERC20.sol",
      "solcConfig": {
        "version": "0.8.9",
        "settings": {
          "optimizer": {
            "enabled": false,
            "runs": 200
          },
          "outputSelection": {
            "*": {
              "*": [
                "abi",
                "evm.bytecode",
                "evm.deployedBytecode",
                "evm.methodIdentifiers",
                "metadata"
              ],
              "": [
                "ast"
              ]
            }
          }
        }
      },
      "imports": [
        "@openzeppelin/contracts/token/ERC20/ERC20.sol",
        "@openzeppelin/contracts/access/Ownable.sol"
      ],
      "versionPragmas": [
        "^0.8.4"
      ],
      "artifacts": [
        "tradeToken"
      ]
    },
    "D:\\GITHUB REPOS\\TradeContract-Hardhat\\contracts\\Lock.sol": {
      "lastModificationDate": 1672905592062,
      "contentHash": "ae66265769cc28ebdaa34881df95bc5e",
      "sourceName": "contracts/Lock.sol",
      "solcConfig": {
        "version": "0.8.9",
        "settings": {
          "optimizer": {
            "enabled": false,
            "runs": 200
          },
          "outputSelection": {
            "*": {
              "*": [
                "abi",
                "evm.bytecode",
                "evm.deployedBytecode",
                "evm.methodIdentifiers",
                "metadata"
              ],
              "": [
                "ast"
              ]
            }
          }
        }
      },
      "imports": [],
      "versionPragmas": [
        "^0.8.9"
      ],
      "artifacts": [
        "Lock"
      ]
    }
  }
}
